<?xml version="1.0"?>
<location xmlns:xsd="http://www.w3.org/2001/XMLSchema" xmlns:xsi="http://www.w3.org/2001/XMLSchema-instance">
  <items>
    <item name="Ground">
      <transform position_x="0" position_y="0" position_z="0" rotation_x="-0" rotation_y="0" rotation_z="0" scale_x="1" scale_y="1" scale_z="1" />
      <geometry mesh_name="generated_mesh_16512" mesh_link="meshes/mesh_15576_generated_mesh_16512" material_name="generated_material_-36050" material_link="materials/material_-36050_generated_material_-36050" />
    </item>
  </items>
  <transform position_x="80" position_y="0" position_z="-240" rotation_x="-0" rotation_y="0" rotation_z="0" scale_x="1" scale_y="1" scale_z="1" />
  <minimap name="minimap_1_-3" link="minimaps/minimap_1_-3" />
</location>